setup.py
everytrail_export/__init__.py
everytrail_export/cli.py
everytrail_export/scraper.py
everytrail_export.egg-info/PKG-INFO
everytrail_export.egg-info/SOURCES.txt
everytrail_export.egg-info/dependency_links.txt
everytrail_export.egg-info/entry_points.txt
everytrail_export.egg-info/requires.txt
everytrail_export.egg-info/top_level.txt