Metadata-Version: 1.1
Name: everytrail-export
Version: 0.1.3
Summary: scraper for downloading trips from EveryTrail, including GPS data, story, and photos.
Home-page: https://github.com/mddub/everytrail_export
Author: Mark Wilson
Author-email: mark@warkmilson.com
License: MIT
Platform: UNKNOWN
Classifier: Programming Language :: Python
Classifier: Programming Language :: Python :: 2.6
Classifier: Programming Language :: Python :: 2.7
Classifier: Development Status :: 4 - Beta
Classifier: Intended Audience :: End Users/Desktop
Classifier: Environment :: Console
Classifier: Operating System :: OS Independent
Classifier: License :: OSI Approved :: MIT License
